LICENSE
README.md
clusterstate.py
setup.py
ClusterState.egg-info/PKG-INFO
ClusterState.egg-info/SOURCES.txt
ClusterState.egg-info/dependency_links.txt
ClusterState.egg-info/top_level.txt